mser/__init__.py
mser/predict.py
mser/trainer.py
mser/configs/augmentation.yml
mser/configs/bi_lstm.yml
mser/data_utils/__init__.py
mser/data_utils/collate_fn.py
mser/data_utils/featurizer.py
mser/data_utils/reader.py
mser/metric/__init__.py
mser/metric/metrics.py
mser/models/__init__.py
mser/models/base_model.py
mser/models/bi_lstm.py
mser/optimizer/__init__.py
mser/optimizer/scheduler.py
mser/utils/__init__.py
mser/utils/checkpoint.py
mser/utils/emotion2vec_predict.py
mser/utils/record.py
mser/utils/utils.py
mser-0.0.11.dist-info/LICENSE
mser-0.0.11.dist-info/METADATA
mser-0.0.11.dist-info/WHEEL
mser-0.0.11.dist-info/top_level.txt
mser-0.0.11.dist-info/RECORD
